{
  "project_info": {
    "project_number": "512078342486",
    "project_id": "livevideowallpaper-906d8",
    "storage_bucket": "livevideowallpaper-906d8.appspot.com"
  },
  "client": [
    {
      "client_info": {
        "mobilesdk_app_id": "1:512078342486:android:7bcc82aac382d852f28ef7",
        "android_client_info": {
          "package_name": "video.wallpaper.videotolive.maker"
        }
      },
      "oauth_client": [
        {
          "client_id": "512078342486-oa51h62ao6dapu02shvl198qgdns79ms.apps.googleusercontent.com",
          "client_type": 3
        }
      ],
      "api_key": [
        {
          "current_key": "AIzaSyBXSYEj_cucBskQ57cmb_WiWChYk_WjAT8"
        }
      ],
      "services": {
        "appinvite_service": {
          "other_platform_oauth_client": [
            {
              "client_id": "512078342486-oa51h62ao6dapu02shvl198qgdns79ms.apps.googleusercontent.com",
              "client_type": 3
            }
          ]
        }
      }
    }
  ],
  "configuration_version": "1"
}